cpu/utils/encordings.v
// ALU
`define FORWARD 5'b00000
`define ADD 5'b00001
`define SUB 5'b00010
`define SLL 5'b00011
`define SLT 5'b00100
`define SLTU 5'b00101
`define XOR 5'b00110
`define SRL 5'b00111
`define SRA 5'b01000
`define OR 5'b01001
`define AND 5'b01010
`define MUL 5'b01011
`define MULH 5'b01100
`define MULHSU 5'b01101
`define MULHU 5'b01110
`define DIV 5'b01111
`define DIVU 5'b10000
`define REM 5'b10001
`define REMU 5'b10010

// immediate encoding of the values of the type
`define I_TYPE = 3'b000
`define S_TYPE = 3'b001
`define B_TYPE = 3'b010
`define U_TYPE = 3'b011
`define J_TYPE = 3'b100

cpu/pipeline_regs/ex_mem_pipeline_reg.v
module ex_mem_pipeline_reg(
    input clk, rst, reg_write_ex_in,
    input [31:0] pc_ex_in, alu_result_ex_in, read_data2_ex_in, imm_ex_in,
    input [4:0] dest_addr_ex_in,
    input [3:0] read_write_ex_in,
    input [1:0] WB_sel_ex_in,
    output reg reg_write_mem_out,
    output reg [31:0] pc_mem_out, alu_result_mem_out, read_data2_mem_out, imm_mem_out,
    output reg [4:0] dest_addr_mem_out,
    output reg [3:0] read_write_mem_out,
    output reg [1:0] WB_sel_mem_out
);
    always @(posedge clk or posedge rst) begin
        if (rst) begin
            reg_write_mem_out <= 1'b0;
            dest_addr_mem_out <= 32'b0;
            pc_mem_out <= 32'b0;
            alu_result_mem_out <= 32'b0;
            read_data2_mem_out <= 32'b0;
            imm_mem_out <= 32'b0;
            read_write_mem_out <= 4'b0;
            WB_sel_mem_out <= 2'b0;
        end
        else begin
            reg_write_mem_out <= reg_write_ex_in;
            dest_addr_mem_out <= dest_addr_ex_in;
            pc_mem_out <= pc_ex_in;
            alu_result_mem_out <= alu_result_ex_in;
            read_data2_mem_out <= read_data2_ex_in;
            imm_mem_out <= imm_ex_in;
            read_write_mem_out <= read_write_ex_in;
            WB_sel_mem_out <= WB_sel_ex_in;
        end
    end

endmodule

cpu/EX_stage/branch/branch_logic.v
`ifdef TB_RUN
    `include "../../utils/encordings.v"
`else
    `include "./utils/encordings.v"
`endif


module branch_logic (
    input wire [31:0] data1,
    input wire [31:0] data2,
    input wire [2:0] op,
    output wire out
);

    assign #2  out = (op == `BEQ && (data1 == data2)) ||
                 (op == `BNE && (data1 != data2)) ||
                 (op == `BLT && ($signed(data1) < $signed(data2))) || 
                 (op == `BGE && ($signed(data1) >= $signed(data2))) || 
                 (op == `BLTU && ($unsigned(data1) < $unsigned(data2))) ||
                 (op == `BGEU && ($unsigned(data1) >= $unsigned(data2))) ||
                 (op == `JAL_JALR);
    
endmodule

cpu/EX_stage/alu.v
`include "../utils/encordings.v"
`timescale 1ns/100ps

// ALU module
module alu(DATA1, DATA2, SELECT, RESULT);

    // initailize input ports
    input [31:0] DATA1, DATA2;
    wire [31:0] UDATA1, UDATA2;
    input [4:0] SELECT;
    // initailize output ports
    output reg  [31:0] RESULT;

    // define the wires
    wire [31:0] forwardData, addData, subData, sllData, sltData, sltuData, xorData, srlData, sraData, orData, andData, mulData, mulhData, mulhuData, mulhsuData, divData, divuData, remData, remuData;

    assign #1 forwardData = DATA1;
    assign #2 addData = DATA1 + DATA2;
    assign #2 subData = DATA1 - DATA2;

    assign #1 sltData = ($signed(DATA1) < $signed(DATA2))?32'd1:32'd0;
    assign #1 sltuData = ($unsigned(DATA1) < $unsigned(DATA2))?32'd1:32'd0;

    assign #1 sllData = DATA1 << DATA2;
    assign #1 srlData = DATA1 >> DATA2;
    assign #1 sraData = DATA1 >>> DATA2;

    assign #1 xorData = DATA1 ^ DATA2;
    assign #1 orData = DATA1 | DATA2;
    assign #1 andData = DATA1 & DATA2;
    assign #3 mulData = DATA1 * DATA2;

    assign #3 mulhData = (DATA1 * DATA2)>>32;
    assign #3 mulhsuData = ($signed(DATA1) * $unsigned(DATA2))>>32;
    assign #3 mulhuData = ($unsigned(DATA1) * $unsigned(DATA2))>>32;

    assign #3 divData = DATA1 / DATA2;
    assign #3 divuData = $unsigned(DATA1) / $unsigned(DATA2);
    assign #3 remData = DATA1 % DATA2;
    assign #3 remuData = $unsigned(DATA1) % $unsigned(DATA2);

    always @(*) 
    begin
        case(SELECT)

            `FORWARD: RESULT = forwardData;
            `ADD: RESULT = addData;
            `SUB: RESULT = subData;
            `SLL: RESULT = sllData;
            `SLT: RESULT = sltData;
            `SLTU: RESULT = sltuData;
            `XOR: RESULT = xorData;
            `SRL: RESULT = srlData;
            `SRA: RESULT = sraData;
            `OR: RESULT = orData;
            `AND: RESULT = andData;
            `MUL: RESULT = mulData;
            `MULH: RESULT = mulhData;
            `MULHSU: RESULT = mulhsuData;
            `MULHU: RESULT = mulhuData;
            `DIV: RESULT = divData;
            `DIVU: RESULT = divuData;
            `REM: RESULT = remData;
            `REMU: RESULT = remuData;

            default RESULT = 0;

        endcase
        
    end

endmodule

cpu/utils/mux_32b_2to1.v
`timescale 1ns/100ps

module mux_32b_2to1(
    input [31:0] a,
    input [31:0] b,
    input sel,
    output [31:0] out
);
    assign out = (sel == 1'b1) ? b : a;
endmodule

cpu/EX_stage/EX_stage_tb.v
`include "./alu/alu.v"
`include "./branch/branch_logic.v"
`include "../pipeline_regs/ex_mem_pipeline_reg.v"
`include "../utils/mux_32b_2to1.v"
`include "../utils/encordings.v"
`timescale 1ns/100ps

module EX_stage_tb ();
    reg clk, rst, data1alusel_ex_out, data2alusel_ex_out, reg_write_en_ex_out;
    reg [31:0] pc_ex_out, data1_ex_out, data2_ex_out, imm_ex_out;
    reg [4:0] dest_addr_ex_out, aluop_ex_out;
    reg [2:0] branch_jump_ex_out;
    reg [3:0] read_write_ex_out;
    reg [1:0] WB_sel_ex_out;

    wire [31:0] data1_mux_out, data2_mux_out, alu_res_out;
    wire branch_logic_out;

    mux_32b_2to1 data1_mux (
        .a(data1_ex_out),
        .b(pc_ex_out),
        .sel(data1alusel_ex_out),
        .out(data1_mux_out)
    );

    mux_32b_2to1 data2_mux (
        .a(data2_ex_out),
        .b(imm_ex_out),
        .sel(data2alusel_ex_out),
        .out(data2_mux_out)
    );

    alu alu_inst (
        .DATA1(data1_mux_out),
        .DATA2(data2_mux_out),
        .SELECT(aluop_ex_out),
        .RESULT(alu_res_out)
    );

    branch_logic branch_logic_inst (
        .data1(data1_ex_out),
        .data2(data2_ex_out),
        .op(branch_jump_ex_out),
        .out(branch_logic_out)
    );

    ex_mem_pipeline_reg ex_mem_pipeline_reg_inst (
        .clk(clk),
        .rst(rst),
        .reg_write_ex_in(reg_write_en_ex_out),
        .pc_ex_in(pc_ex_out),
        .alu_result_ex_in(alu_res_out),
        .read_data2_ex_in(data2_mux_out),
        .imm_ex_in(imm_ex_out),
        .dest_addr_ex_in(dest_addr_ex_out),
        .read_write_ex_in(read_write_ex_out),
        .WB_sel_ex_in(WB_sel_ex_out),
        .reg_write_mem_out(),
        .pc_mem_out(),
        .alu_result_mem_out(),
        .read_data2_mem_out(),
        .imm_mem_out(),
        .dest_addr_mem_out(),
        .read_write_mem_out(),
        .WB_sel_mem_out()
    );

    initial begin
        $dumpfile("EX_stage_tb.vcd");
        $dumpvars(0, EX_stage_tb);

        // Initialize all inputs
        clk = 0;
        rst = 1;
        data1alusel_ex_out = 0;
        data2alusel_ex_out = 0;
        reg_write_en_ex_out = 0;
        pc_ex_out = 32'h00000000;
        data1_ex_out = 32'h00000000;
        data2_ex_out = 32'h00000000;
        imm_ex_out = 32'h00000000;
        dest_addr_ex_out = 5'b00000;
        aluop_ex_out = 5'b00000;
        branch_jump_ex_out = 3'b000;
        read_write_ex_out = 4'b0000;
        WB_sel_ex_out = 2'b00;

        // Release reset after a few clock cycles
        #10 rst = 0;

        // Test case 1: Simple ALU operation (ADD)
        #10;
        data1_ex_out = 32'h00000001;
        data2_ex_out = 32'h00000002;
        aluop_ex_out = `ADD; // Assuming 5'b00000 is the opcode for ADD
        #10;
        $display("Test case 1: ALU ADD operation");
        $display("data1_ex_out = %h, data2_ex_out = %h, alu_res_out = %h", data1_mux_out, data2_ex_out, alu_res_out);

        // Test case 2: ALU operation with immediate (SUB)
        #10;
        data1_ex_out = 32'h00000005;
        imm_ex_out = 32'h00000002;
        data2alusel_ex_out = 1; // Select immediate
        aluop_ex_out = `SUB; // Assuming 5'b00001 is the opcode for SUB
        #10;
        $display("Test case 2: ALU SUB operation with immediate");
        $display("data1_ex_out = %h, imm_ex_out = %h, alu_res_out = %h", data1_ex_out, imm_ex_out, alu_res_out);

        // Test case 3: Branch logic (BEQ)
        #10;
        data1_ex_out = 32'h00000003;
        data2_ex_out = 32'h00000003;
        branch_jump_ex_out = `BEQ; // Assuming 3'b001 is the opcode for BEQ
        #10;
        $display("Test case 3: Branch logic BEQ");
        $display("data1_ex_out = %h, data2_ex_out = %h, branch_logic_out = %b", data1_ex_out, data2_ex_out, branch_logic_out);

        // Test case 4: Branch logic (BNE)
        #10;
        data1_ex_out = 32'h00000004;
        data2_ex_out = 32'h00000005;
        branch_jump_ex_out = `BNE; // Assuming 3'b010 is the opcode for BNE
        #10;
        $display("Test case 4: Branch logic BNE");
        $display("data1_ex_out = %h, data2_ex_out = %h, branch_logic_out = %b", data1_ex_out, data2_ex_out, branch_logic_out);

        // End simulation
        #10 $finish;
    end

    // Clock generation
    always #5 clk = ~clk;

endmodule

cpu/EX_stage/EX_stage_tb.vcd
$date
	Thu Jan 30 00:55:06 2025
$end
$version
	Icarus Verilog
$end
$timescale
	100ps
$end
$scope module EX_stage_tb $end
$var wire 32 ! data2_mux_out [31:0] $end
$var wire 32 " data1_mux_out [31:0] $end
$var wire 1 # branch_logic_out $end
$var wire 32 $ alu_res_out [31:0] $end
$var reg 2 % WB_sel_ex_out [1:0] $end
$var reg 5 & aluop_ex_out [4:0] $end
$var reg 3 ' branch_jump_ex_out [2:0] $end
$var reg 1 ( clk $end
$var reg 32 ) data1_ex_out [31:0] $end
$var reg 1 * data1alusel_ex_out $end
$var reg 32 + data2_ex_out [31:0] $end
$var reg 1 , data2alusel_ex_out $end
$var reg 5 - dest_addr_ex_out [4:0] $end
$var reg 32 . imm_ex_out [31:0] $end
$var reg 32 / pc_ex_out [31:0] $end
$var reg 4 0 read_write_ex_out [3:0] $end
$var reg 1 1 reg_write_en_ex_out $end
$var reg 1 2 rst $end
$scope module alu_inst $end
$var wire 5 3 SELECT [4:0] $end
$var wire 32 4 andData [31:0] $end
$var wire 32 5 forwardData [31:0] $end
$var wire 32 6 mulhData [31:0] $end
$var wire 32 7 mulhsuData [31:0] $end
$var wire 32 8 mulhuData [31:0] $end
$var wire 32 9 orData [31:0] $end
$var wire 32 : xorData [31:0] $end
$var wire 32 ; subData [31:0] $end
$var wire 32 < srlData [31:0] $end
$var wire 32 = sraData [31:0] $end
$var wire 32 > sltuData [31:0] $end
$var wire 32 ? sltData [31:0] $end
$var wire 32 @ sllData [31:0] $end
$var wire 32 A remuData [31:0] $end
$var wire 32 B remData [31:0] $end
$var wire 32 C mulData [31:0] $end
$var wire 32 D divuData [31:0] $end
$var wire 32 E divData [31:0] $end
$var wire 32 F addData [31:0] $end
$var wire 32 G DATA2 [31:0] $end
$var wire 32 H DATA1 [31:0] $end
$var reg 32 I RESULT [31:0] $end
$upscope $end
$scope module branch_logic_inst $end
$var wire 32 J data1 [31:0] $end
$var wire 32 K data2 [31:0] $end
$var wire 3 L op [2:0] $end
$var wire 1 # out $end
$upscope $end
$scope module data1_mux $end
$var wire 32 M a [31:0] $end
$var wire 32 N b [31:0] $end
$var wire 1 * sel $end
$var wire 32 O out [31:0] $end
$upscope $end
$scope module data2_mux $end
$var wire 32 P a [31:0] $end
$var wire 32 Q b [31:0] $end
$var wire 1 , sel $end
$var wire 32 R out [31:0] $end
$upscope $end
$scope module ex_mem_pipeline_reg_inst $end
$var wire 2 S WB_sel_ex_in [1:0] $end
$var wire 32 T alu_result_ex_in [31:0] $end
$var wire 1 ( clk $end
$var wire 5 U dest_addr_ex_in [4:0] $end
$var wire 32 V imm_ex_in [31:0] $end
$var wire 32 W pc_ex_in [31:0] $end
$var wire 32 X read_data2_ex_in [31:0] $end
$var wire 4 Y read_write_ex_in [3:0] $end
$var wire 1 1 reg_write_ex_in $end
$var wire 1 2 rst $end
$var reg 2 Z WB_sel_mem_out [1:0] $end
$var reg 32 [ alu_result_mem_out [31:0] $end
$var reg 5 \ dest_addr_mem_out [4:0] $end
$var reg 32 ] imm_mem_out [31:0] $end
$var reg 32 ^ pc_mem_out [31:0] $end
$var reg 32 _ read_data2_mem_out [31:0] $end
$var reg 4 ` read_write_mem_out [3:0] $end
$var reg 1 a reg_write_mem_out $end
$upscope $end
$upscope $end
$enddefinitions $end
$comment Show the parameter values. $end
$dumpall
$end
#0
$dumpvars
0a
b0 `
b0 _
b0 ^
b0 ]
b0 \
b0 [
b0 Z
b0 Y
b0 X
b0 W
b0 V
b0 U
bx T
b0 S
b0 R
b0 Q
b0 P
b0 O
b0 N
b0 M
b0 L
b0 K
b0 J
bx I
b0 H
b0 G
bx F
bx E
bx D
bx C
bx B
bx A
bx @
bx ?
bx >
bx =
bx <
bx ;
bx :
bx 9
bx 8
bx 7
bx 6
bx 5
bx 4
b0 3
12
01
b0 0
b0 /
b0 .
b0 -
0,
b0 +
0*
b0 )
0(
b0 '
b0 &
b0 %
bx $
1#
b0 "
b0 !
$end
#10
b0 $
b0 I
b0 T
b0 4
b0 9
b0 :
b0 =
b0 <
b0 @
b0 5
b0 >
b0 ?
#20
b0 ;
b0 F
#30
b0 C
b0 8
b0 7
b0 6
#50
1(
#100
0(
02
#150
1(
#200
0#
b10 !
b10 G
b10 R
b10 X
b1 "
b1 H
b1 O
0(
b1 &
b1 3
b10 +
b10 K
b10 P
b1 )
b1 J
b1 M
#210
b1 >
b1 ?
b11 9
b11 :
b100 @
b1 5
#220
b11 $
b11 I
b11 T
b11111111111111111111111111111111 ;
b11 F
#230
b1 A
b1 B
b0 D
b0 E
b10 C
#250
b10 _
b11 [
1(
#300
0(
#350
1(
#400
b11111111111111111111111111111111 $
b11111111111111111111111111111111 I
b11111111111111111111111111111111 T
b101 "
b101 H
b101 O
0(
b10 &
b10 3
1,
b10 .
b10 Q
b10 V
b101 )
b101 J
b101 M
#410
b0 >
b0 ?
b111 9
b111 :
b1 =
b1 <
b10100 @
b101 5
#420
b11 $
b11 I
b11 T
b11 ;
b111 F
#430
b10 D
b10 E
b1010 C
#450
b10 ]
1(
#500
0(
#550
1(
#600
1#
b11 "
b11 H
b11 O
0(
b11 +
b11 K
b11 P
b11 )
b11 J
b11 M
#610
b10 4
b11 9
b1 :
b0 =
b0 <
b1100 @
b11 5
#620
b1 $
b1 I
b1 T
b1 ;
b101 F
#630
b1 D
b1 E
b110 C
#650
b1 [
1(
#700
0(
#750
1(
#800
b100 "
b100 H
b100 O
0(
b1 '
b1 L
b101 +
b101 K
b101 P
b100 )
b100 J
b100 M
#810
b0 4
b110 9
b110 :
b1 =
b1 <
b10000 @
b100 5
#820
b10 $
b10 I
b10 T
b10 ;
b110 F
#830
b0 A
b0 B
b10 D
b10 E
b1000 C
#850
b10 [
1(
