cpu/utils/encordings.v
// ALU
`define FORWARD 5'b00000
`define ADD 5'b00001
`define SUB 5'b00010
`define SLL 5'b00011
`define SLT 5'b00100
`define SLTU 5'b00101
`define XOR 5'b00110
`define SRL 5'b00111
`define SRA 5'b01000
`define OR 5'b01001
`define AND 5'b01010
`define MUL 5'b01011
`define MULH 5'b01100
`define MULHSU 5'b01101
`define MULHU 5'b01110
`define DIV 5'b01111
`define DIVU 5'b10000
`define REM 5'b10001
`define REMU 5'b10010

// immediate encoding of the values of the type
`define I_TYPE = 3'b000
`define S_TYPE = 3'b001
`define B_TYPE = 3'b010
`define U_TYPE = 3'b011
`define J_TYPE = 3'b100

cpu/utils/mux_3b_2to1.v
module mux_3b_2to1(
    input [2:0] a,
    input [2:0] b,
    input sel,
    output [2:0] out
);
    assign out = (sel == 1'b1) ? b : a;
endmodule

cpu/ID_stage/control_unit.v
`include "../utils/mux_3b_2to1.v"
`include "../utils/encordings.v"
`timescale 1ns/100ps

module control_unit(opcode, funct3, funct7, alu_op, reg_write_en, mem_write, mem_read, branch_jump, imm_sel, data1_alu_sel, data2_alu_sel, wb_sel, reset);

    input [6:0] opcode;
    input [2:0] funct3;
    input [6:0] funct7;
    input reset; // reset input and alu comparator signal

    // defining output control signals
    output wire reg_write_en, data1_alu_sel, data2_alu_sel;
    output wire [4:0] alu_op;
    output wire [2:0] mem_write;
    output wire [3:0] mem_read;
    output wire [2:0] branch_jump;
    output wire [3:0] imm_sel;
    output wire [1:0] wb_sel; 

    // decoded instruction segments
    wire funct3_mux_select; // to select the alu signal between func3 and predefined values for JAL & AUIPC

    // ALU control signal genaration
    assign #3 funct3_mux_select = (opcode == 7'b0010111) | (opcode == 7'b1101111) | (opcode == 7'b0100011) | (opcode == 7'b0000011) | (opcode == 7'b1100011);
    mux_3b_2to1 funct3_mux (funct3, 3'b000, alu_op[2:0], funct3_mux_select);   
    assign #3 alu_op[4] = ({opcode, funct3, funct7} == {7'b0010011, 3'b101, 7'b0100000}) | ({opcode, funct3, funct7} == {7'b0110011, 3'b000, 7'b0100000}) | ({opcode, funct3, funct7} == {7'b0110011, 3'b101, 7'b0100000}) | (opcode == 7'b0110111);// if SRAI, SUB, SRA, LUI
    assign #3 alu_op[3] = ({opcode, funct7} == 14'b01100110000001) | (opcode == 7'b0110111);  // if MUL_inst or LUI
    
    // Register file write signal geraration
    assign #3 reg_write_en = ~((opcode == 7'b0100011) | (opcode == 7'b1100011) | (opcode == 7'b0000000)) ;    

    // Main memory write signal genaration
    assign #3 mem_write[2] = (opcode == 7'b100011);
    assign #3 mem_write[1:0] = funct3[1:0];

    // Main memory read control signal
    assign #3 mem_read[3] = (opcode == 7'b0000011);
    assign #3 mem_read[2:0] = funct3;

    // branch control signal generation
    assign #3 branch_jump = ((opcode == 7'b1100111) || (opcode == 7'b1101111))?3'b010:funct3; // if JAL or JALR = 010 else funct3 
    
    // Immediate select signal genaration
    assign #3 imm_sel[3] = ({opcode, funct3} == {7'b0000011, 3'b100}) | 
                                 ({opcode, funct3} == {7'b0000011, 3'b101}) | 
                                 ({opcode, funct3} == {7'b0010011, 3'b011}) | 
                                 ({opcode, funct3, funct7} == {7'b0110011, 3'b011, 7'b0000000}) | 
                                 ({opcode, funct3, funct7} == {7'b0110011, 3'b010, 7'b0000001}) | 
                                 ({opcode, funct3, funct7} == {7'b0110011, 3'b011, 7'b0000001}) | 
                                 ({opcode, funct3, funct7} == {7'b0110011, 3'b111, 7'b0000001});

    assign #3 imm_sel[2:0] =  (opcode == 7'b0000011) ? IMM_TYPE3 : 
                                    (opcode == 7'b0010111) ? IMM_TYPE1 :
                                    (opcode == 7'b0100011) ? 3'b100 : 
                                    (opcode == 7'b0110111) ? IMM_TYPE1 : 
                                    (opcode == 7'b1101111) ? IMM_TYPE2 : 
                                    (opcode == 7'b1100111) ? IMM_TYPE3 : 
                                    (opcode == 7'b1100011) ? IMM_TYPE4 : 
                                    ({opcode, funct3} == {7'b0010011, 3'bx01}) ? IMM_TYPE6 : 
                                    (opcode == 7'b0010011) ? IMM_TYPE3 : 3'bxxx;

    // operand 1 and 2 signal genaration
    assign #3 data1_alu_sel = (opcode == 7'b0010111) | (opcode == 7'b1101111) | (opcode == 7'b1100111) | (opcode == 7'b1100011); // if AUIPC, JAL, JALR
    //TODO: test the dont care condition.
    assign #3 data2_alu_sel = (opcode == 7'b0000011) | // all L_inst
                              (opcode == 7'b0010011) | //immediate_inst
                              (opcode == 7'b0010111) | //AUIPC
                              (opcode == 7'b0100011) | //S_inst 
                              (opcode == 7'b0110111) | //LUI
                              (opcode == 7'b1100111) | //JAL , 
                              (opcode == 7'b1101111) | //JALR
                              (opcode == 7'b1100011) ; //B_inst 

    // Register file write mux select signal genaration
    assign #3 wb_sel[0] = ~(opcode == 7'b0000011);
    assign #3 wb_sel[1] = (opcode == 7'b0010111) | (opcode == 7'b1101111) | (opcode == 7'b1100111);


endmodule

cpu/ID_stage/control_unit/control_unit_tb.v
`include "./utils/encordings.v"
`include "./ID_stage/control_unit/control_unit.v"
`timescale 1ns/100ps

module control_unit_tb;

    // Inputs
    reg [6:0] opcode;
    reg [2:0] funct3;
    reg [6:0] funct7;
    reg reset;

    // Outputs
    wire reg_write_en, data1_alu_sel, data2_alu_sel;
    wire [4:0] alu_op;
    wire [2:0] mem_write;
    wire [3:0] mem_read;
    wire [2:0] branch_jump;
    wire [3:0] imm_sel;
    wire [1:0] wb_sel;

    // Instantiate the control_unit module
    control_unit uut (
        .opcode(opcode),
        .funct3(funct3),
        .funct7(funct7),
        .alu_op(alu_op),
        .reg_write_en(reg_write_en),
        .mem_write(mem_write),
        .mem_read(mem_read),
        .branch_jump(branch_jump),
        .imm_sel(imm_sel),
        .data1_alu_sel(data1_alu_sel),
        .data2_alu_sel(data2_alu_sel),
        .wb_sel(wb_sel),
        .reset(reset)
    );

    initial begin
        // Open a file for logging
        $dumpfile("tb_control_unit.vcd");
        $dumpvars(0, control_unit_tb);

        // Monitor to print inputs and outputs
        $monitor("Time: %d | Opcode: %b | Funct3: %b | Funct7: %b | Reset: %b | ALU_OP: %b | RegWrite: %b | MemWrite: %b | MemRead: %b | BranchJump: %b | ImmSel: %b | Data1Sel: %b | Data2Sel: %b | WBSel: %b",
                 $time, opcode, funct3, funct7, reset, alu_op, reg_write_en, mem_write, mem_read, branch_jump, imm_sel, data1_alu_sel, data2_alu_sel, wb_sel);
    end

    // Testbench logic
    initial begin
        #10

        // Initialize inputs
        opcode = 7'b0000000;
        funct3 = 3'b000;
        funct7 = 7'b0000000;
        reset = 0;

        // Test case 1: R-type instruction (ADD)
        #10;
        opcode = `OP_R_TYPE;
        funct3 = 3'b000;
        funct7 = 7'b0000000;
        #10;

        // Test case 2: I-type instruction (ADDI)
        #10;
        opcode = `OP_I_TYPE;
        funct3 = 3'b000;
        funct7 = 7'b0000000;
        #10;

        // Test case 3: Load instruction (LW)
        #10;
        opcode = `OP_LOAD;
        funct3 = 3'b010;
        funct7 = 7'b0000000;
        #10;

        // Test case 4: Store instruction (SW)
        #10;
        opcode = `OP_STORE;
        funct3 = 3'b010;
        funct7 = 7'b0000000;
        #10;

        // Test case 5: Branch instruction (BEQ)
        #10;
        opcode = `OP_BRANCH;
        funct3 = 3'b000;
        funct7 = 7'b0000000;
        #10;

        // Test case 6: JAL instruction
        #10;
        opcode = `OP_JAL;
        funct3 = 3'b000;
        funct7 = 7'b0000000;
        #10;

        // Test case 7: LUI instruction
        #10;
        opcode = `OP_LUI;
        funct3 = 3'b000;
        funct7 = 7'b0000000;
        #10;

        // Test case 8: AUIPC instruction
        #10;
        opcode = `OP_AUIPC;
        funct3 = 3'b000;
        funct7 = 7'b0000000;
        #10;

        // Test case 9: Reset condition
        #10;
        reset = 1;
        #10;
        reset = 0;
        #10;

        // End simulation
        $finish;
    end

endmodule

cpu/tb_control_unit.vcd
$date
	Thu Jan 30 16:40:11 2025
$end
$version
	Icarus Verilog
$end
$timescale
	100ps
$end
$scope module control_unit_tb $end
$var wire 2 ! wb_sel [1:0] $end
$var wire 1 " reg_write_en $end
$var wire 3 # mem_write [2:0] $end
$var wire 4 $ mem_read [3:0] $end
$var wire 4 % imm_sel [3:0] $end
$var wire 1 & data2_alu_sel $end
$var wire 1 ' data1_alu_sel $end
$var wire 3 ( branch_jump [2:0] $end
$var wire 5 ) alu_op [4:0] $end
$var reg 3 * funct3 [2:0] $end
$var reg 7 + funct7 [6:0] $end
$var reg 7 , opcode [6:0] $end
$var reg 1 - reset $end
$scope module uut $end
$var wire 1 ' data1_alu_sel $end
$var wire 1 & data2_alu_sel $end
$var wire 3 . funct3 [2:0] $end
$var wire 1 / funct3_mux_select $end
$var wire 7 0 funct7 [6:0] $end
$var wire 7 1 opcode [6:0] $end
$var wire 1 " reg_write_en $end
$var wire 1 - reset $end
$var wire 2 2 wb_sel [1:0] $end
$var wire 3 3 mem_write [2:0] $end
$var wire 4 4 mem_read [3:0] $end
$var wire 4 5 imm_sel [3:0] $end
$var wire 3 6 branch_jump [2:0] $end
$var wire 5 7 alu_op [4:0] $end
$scope module funct3_mux $end
$var wire 3 8 a [2:0] $end
$var wire 3 9 b [2:0] $end
$var wire 1 / sel $end
$var wire 3 : out [2:0] $end
$upscope $end
$upscope $end
$upscope $end
$enddefinitions $end
$comment Show the parameter values. $end
$dumpall
$end
#0
$dumpvars
bx :
b0 9
bx 8
bx 7
bx 6
bx 5
bx 4
bx 3
bx 2
bx 1
bx 0
x/
bx .
x-
bx ,
bx +
bx *
bx )
bx (
x'
x&
bx %
bx $
bx #
x"
bx !
$end
#100
bx000 )
bx000 7
b0 :
0-
b0 +
b0 0
b0 *
b0 .
b0 8
b0 ,
b0 1
#130
0&
b0xxx %
b0xxx 5
0/
0'
0"
b1 !
b1 2
b0 (
b0 6
b0 )
b0 7
b0 #
b0 3
b0 $
b0 4
#200
b110011 ,
b110011 1
#230
1"
#400
b10011 ,
b10011 1
#430
b10 %
b10 5
1&
#600
b10 )
b10 7
b10 :
b10 *
b10 .
b10 8
b11 ,
b11 1
#630
b0 )
b0 7
b0 :
1/
b0 !
b0 2
b10 #
b10 3
b10 (
b10 6
b1010 $
b1010 4
#800
b100011 ,
b100011 1
#830
0"
b1 !
b1 2
b100 %
b100 5
b110 #
b110 3
b10 $
b10 4
#1000
b0 *
b0 .
b0 8
b1100011 ,
b1100011 1
#1030
b11 %
b11 5
b0 (
b0 6
1'
b0 $
b0 4
b0 #
b0 3
#1200
b1101111 ,
b1101111 1
#1230
b1 %
b1 5
1"
b10 (
b10 6
b11 !
b11 2
#1400
b110111 ,
b110111 1
#1430
0/
b0 %
b0 5
0'
b0 (
b0 6
b10 !
b10 2
b11000 )
b11000 7
#1600
b10111 ,
b10111 1
#1630
1/
1'
b1 !
b1 2
b0 )
b0 7
#1800
1-
#1900
0-
