cpu/pipeline_regs/if_id_pipeline_reg.v
module if_id_pipeline_reg(clk, rst, pc_in, pc_out, instr_in, instr_out);
    input clk, rst;
    input [31:0] pc_in, instr_in;
    output reg [31:0] pc_out, instr_out;

    always @(posedge clk) begin
        if (rst == 1'b1) begin
            pc_out <= 32'dx;
            instr_out <= 32'dx;
        end
        else begin
            pc_out <= pc_in;
            instr_out <= instr_in;
        end
    end
endmodule

cpu/IF_stage/imem.v
// instruction memmory with memfile
module imem(clk, rst, pc, instr);
    input clk, rst;
    input [31:0] pc;
    output reg [31:0] instr;

    reg [31:0] mem[0:1023];

    initial begin
        $readmemh("memfile.mem", mem);
    end

    always @(posedge clk) begin
        if (rst == 1'b1) begin
            instr <= 32'dx;
        end
        else begin
            instr <= mem[pc[31:2]];
        end
    end
endmodule

cpu/utils/adder_32b_4.v
`timescale 1ns/100ps

module adder_32b_4(
    input [31:0] data,
    output [31:0] out
);

    assign out = data + 4;

endmodule

cpu/utils/mux_32b_2to1.v
`timescale 1ns/100ps

module mux_32b_2to1(
    input [31:0] a,
    input [31:0] b,
    input sel,
    output [31:0] out
);
    assign out = (sel == 1'b1) ? b : a;
endmodule

cpu/IF_stage/pc.v
module pc(clk, rst, pc_in, pc_out);
    input clk, rst;
    input [31:0] pc_in;
    output reg [31:0] pc_out;

    always @(posedge clk) begin
        if (rst == 1'b1) begin
            pc_out <= 32'h0;
        end
        else begin
            pc_out <= pc_in;
        end
    end
endmodule

cpu/IF_stage/test_stage/fetch_stage_tb.v
`include "./IF_stage/pc/pc.v"
`include "./pipeline_regs/if_id_pipeline_reg.v"
`include "./utils/mux_32b_2to1.v"
`include "./utils/adder_32b_4.v"
`include "./IF_stage/i_mem/imem.v"
`timescale 1ns/100ps

module fetch_stage_tb;
    reg clk, rst, pc_sel_ex;
    wire [31:0] pc_ex;
    wire [31:0] pc_mux_out, pc_out, pc_next, instr_out, pc_out_dec, instr_out_dec;

    pc pc_(
        .clk(clk), 
        .rst(rst), 
        .pc_in(pc_mux_out), 
        .pc_out(pc_out)
    );

    mux_32b_2to1 pc_mux(
        .a(pc_ex), 
        .b(pc_ex), 
        .sel(pc_sel_ex), 
        .out(pc_mux_out)
    );

    adder_32b_4 pc_adder(
        .data(pc_out), 
        .out(pc_ex)
    );

    imem imem(
        .clk(clk), 
        .rst(rst), 
        .pc(pc_out), 
        .instr(instr_out)
    );   
     
    if_id_pipeline_reg if_id_pipeline_reg(
        .clk(clk), 
        .rst(rst), 
        .pc_in(pc_out), 
        .pc_out(pc_out_dec), 
        .instr_in(instr_out), 
        .instr_out(instr_out_dec)
    );

    initial begin
        $dumpfile("fetch_stage_tb.vcd");
        $dumpvars(0, fetch_stage_tb);
        clk = 1'b0;
        rst = 1'b0;
        pc_sel_ex = 1'b0;
        #5
        rst = 1'b1;
        #10
        rst = 1'b0;
        #500
        $finish;
    end

    always begin
        #10 clk = ~clk;
    end
    
endmodule

cpu/IF_stage/test_stage/fetch_stage_tb.vcd
$date
	Thu Jan 30 16:04:05 2025
$end
$version
	Icarus Verilog
$end
$timescale
	100ps
$end
$scope module fetch_stage_tb $end
$var wire 32 ! pc_out_dec [31:0] $end
$var wire 32 " pc_out [31:0] $end
$var wire 32 # pc_mux_out [31:0] $end
$var wire 32 $ pc_ex [31:0] $end
$var wire 32 % instr_out_dec [31:0] $end
$var wire 32 & instr_out [31:0] $end
$var reg 1 ' clk $end
$var reg 1 ( pc_sel_ex $end
$var reg 1 ) rst $end
$scope module if_id_pipeline_reg $end
$var wire 1 ' clk $end
$var wire 1 ) rst $end
$var wire 32 * pc_in [31:0] $end
$var wire 32 + instr_in [31:0] $end
$var reg 32 , instr_out [31:0] $end
$var reg 32 - pc_out [31:0] $end
$upscope $end
$scope module imem $end
$var wire 1 ' clk $end
$var wire 1 ) rst $end
$var wire 32 . pc [31:0] $end
$var reg 32 / instr [31:0] $end
$upscope $end
$scope module pc_ $end
$var wire 1 ' clk $end
$var wire 1 ) rst $end
$var wire 32 0 pc_in [31:0] $end
$var reg 32 1 pc_out [31:0] $end
$upscope $end
$scope module pc_adder $end
$var wire 32 2 data [31:0] $end
$var wire 32 3 out [31:0] $end
$upscope $end
$scope module pc_mux $end
$var wire 32 4 a [31:0] $end
$var wire 32 5 b [31:0] $end
$var wire 1 ( sel $end
$var wire 32 6 out [31:0] $end
$upscope $end
$upscope $end
$enddefinitions $end
$comment Show the parameter values. $end
$dumpall
$end
#0
$dumpvars
bx 6
bx 5
bx 4
bx 3
bx 2
bx 1
bx 0
bx /
bx .
bx -
bx ,
bx +
bx *
0)
0(
0'
bx &
bx %
bx $
bx #
bx "
bx !
$end
#50
1)
#100
b100 #
b100 0
b100 6
b100 $
b100 3
b100 4
b100 5
b0 "
b0 *
b0 .
b0 1
b0 2
1'
#150
0)
#200
0'
#300
b1000 #
b1000 0
b1000 6
b0 !
b0 -
b10010011 &
b10010011 +
b10010011 /
b1000 $
b1000 3
b1000 4
b1000 5
b100 "
b100 *
b100 .
b100 1
b100 2
1'
#400
0'
#500
b1100 #
b1100 0
b1100 6
b1100 $
b1100 3
b1100 4
b1100 5
b1000 "
b1000 *
b1000 .
b1000 1
b1000 2
b100000000000100010011 &
b100000000000100010011 +
b100000000000100010011 /
b10010011 %
b10010011 ,
b100 !
b100 -
1'
#600
0'
#700
b10000 #
b10000 0
b10000 6
b100000000000100010011 %
b100000000000100010011 ,
b1000 !
b1000 -
b1000001000000110110011 &
b1000001000000110110011 +
b1000001000000110110011 /
b10000 $
b10000 3
b10000 4
b10000 5
b1100 "
b1100 *
b1100 .
b1100 1
b1100 2
1'
#800
0'
#900
b10100 #
b10100 0
b10100 6
b10100 $
b10100 3
b10100 4
b10100 5
b10000 "
b10000 *
b10000 .
b10000 1
b10000 2
b1100010000000100110011 &
b1100010000000100110011 +
b1100010000000100110011 /
b1000001000000110110011 %
b1000001000000110110011 ,
b1100 !
b1100 -
1'
#1000
0'
#1100
b11000 #
b11000 0
b11000 6
b1100010000000100110011 %
b1100010000000100110011 ,
b10000 !
b10000 -
b10000011010000000100011 &
b10000011010000000100011 +
b10000011010000000100011 /
b11000 $
b11000 3
b11000 4
b11000 5
b10100 "
b10100 *
b10100 .
b10100 1
b10100 2
1'
#1200
0'
#1300
b11100 #
b11100 0
b11100 6
b11100 $
b11100 3
b11100 4
b11100 5
b11000 "
b11000 *
b11000 .
b11000 1
b11000 2
b1000000001100111 &
b1000000001100111 +
b1000000001100111 /
b10000011010000000100011 %
b10000011010000000100011 ,
b10100 !
b10100 -
1'
#1400
0'
#1500
b100000 #
b100000 0
b100000 6
b1000000001100111 %
b1000000001100111 ,
b11000 !
b11000 -
bx &
bx +
bx /
b100000 $
b100000 3
b100000 4
b100000 5
b11100 "
b11100 *
b11100 .
b11100 1
b11100 2
1'
#1600
0'
#1700
b100100 #
b100100 0
b100100 6
b100100 $
b100100 3
b100100 4
b100100 5
b100000 "
b100000 *
b100000 .
b100000 1
b100000 2
bx %
bx ,
b11100 !
b11100 -
1'
#1800
0'
#1900
b101000 #
b101000 0
b101000 6
b100000 !
b100000 -
b101000 $
b101000 3
b101000 4
b101000 5
b100100 "
b100100 *
b100100 .
b100100 1
b100100 2
1'
#2000
0'
#2100
b101100 #
b101100 0
b101100 6
b101100 $
b101100 3
b101100 4
b101100 5
b101000 "
b101000 *
b101000 .
b101000 1
b101000 2
b100100 !
b100100 -
1'
#2200
0'
#2300
b110000 #
b110000 0
b110000 6
b101000 !
b101000 -
b110000 $
b110000 3
b110000 4
b110000 5
b101100 "
b101100 *
b101100 .
b101100 1
b101100 2
1'
#2400
0'
#2500
b110100 #
b110100 0
b110100 6
b110100 $
b110100 3
b110100 4
b110100 5
b110000 "
b110000 *
b110000 .
b110000 1
b110000 2
b101100 !
b101100 -
1'
#2600
0'
#2700
b111000 #
b111000 0
b111000 6
b110000 !
b110000 -
b111000 $
b111000 3
b111000 4
b111000 5
b110100 "
b110100 *
b110100 .
b110100 1
b110100 2
1'
#2800
0'
#2900
b111100 #
b111100 0
b111100 6
b111100 $
b111100 3
b111100 4
b111100 5
b111000 "
b111000 *
b111000 .
b111000 1
b111000 2
b110100 !
b110100 -
1'
#3000
0'
#3100
b1000000 #
b1000000 0
b1000000 6
b111000 !
b111000 -
b1000000 $
b1000000 3
b1000000 4
b1000000 5
b111100 "
b111100 *
b111100 .
b111100 1
b111100 2
1'
#3200
0'
#3300
b1000100 #
b1000100 0
b1000100 6
b1000100 $
b1000100 3
b1000100 4
b1000100 5
b1000000 "
b1000000 *
b1000000 .
b1000000 1
b1000000 2
b111100 !
b111100 -
1'
#3400
0'
#3500
b1001000 #
b1001000 0
b1001000 6
b1000000 !
b1000000 -
b1001000 $
b1001000 3
b1001000 4
b1001000 5
b1000100 "
b1000100 *
b1000100 .
b1000100 1
b1000100 2
1'
#3600
0'
#3700
b1001100 #
b1001100 0
b1001100 6
b1001100 $
b1001100 3
b1001100 4
b1001100 5
b1001000 "
b1001000 *
b1001000 .
b1001000 1
b1001000 2
b1000100 !
b1000100 -
1'
#3800
0'
#3900
b1010000 #
b1010000 0
b1010000 6
b1001000 !
b1001000 -
b1010000 $
b1010000 3
b1010000 4
b1010000 5
b1001100 "
b1001100 *
b1001100 .
b1001100 1
b1001100 2
1'
#4000
0'
#4100
b1010100 #
b1010100 0
b1010100 6
b1010100 $
b1010100 3
b1010100 4
b1010100 5
b1010000 "
b1010000 *
b1010000 .
b1010000 1
b1010000 2
b1001100 !
b1001100 -
1'
#4200
0'
#4300
b1011000 #
b1011000 0
b1011000 6
b1010000 !
b1010000 -
b1011000 $
b1011000 3
b1011000 4
b1011000 5
b1010100 "
b1010100 *
b1010100 .
b1010100 1
b1010100 2
1'
#4400
0'
#4500
b1011100 #
b1011100 0
b1011100 6
b1011100 $
b1011100 3
b1011100 4
b1011100 5
b1011000 "
b1011000 *
b1011000 .
b1011000 1
b1011000 2
b1010100 !
b1010100 -
1'
#4600
0'
#4700
b1100000 #
b1100000 0
b1100000 6
b1011000 !
b1011000 -
b1100000 $
b1100000 3
b1100000 4
b1100000 5
b1011100 "
b1011100 *
b1011100 .
b1011100 1
b1011100 2
1'
#4800
0'
#4900
b1100100 #
b1100100 0
b1100100 6
b1100100 $
b1100100 3
b1100100 4
b1100100 5
b1100000 "
b1100000 *
b1100000 .
b1100000 1
b1100000 2
b1011100 !
b1011100 -
1'
#5000
0'
#5100
b1101000 #
b1101000 0
b1101000 6
b1100000 !
b1100000 -
b1101000 $
b1101000 3
b1101000 4
b1101000 5
b1100100 "
b1100100 *
b1100100 .
b1100100 1
b1100100 2
1'
